{
    "肝兪" : [
      {
        "配穴" : "期門",
        "治療" : "肝臟疾病，脅肋痛"
      },
      {
        "配穴" : "百會、太衝",
        "治療" : "頭昏，頭痛，眩暈"
      },
      {
        "配穴" : "腎兪、太谿",
        "治療" : "健忘，失眠"
      },
      {
        "配穴" : "大椎、曲池",
        "治療" : "癲癇"
      },
      {
        "配穴" : "太衝",
        "治療" : "肝脹"
      },
      {
        "配穴" : "胞肓",
        "治療" : "少腹滿"
      },
      {
        "配穴" : "商陽",
        "治療" : "青盲無所見"
      },
      {
        "配穴" : "足三里",
        "治療" : "目昏花"
      },
      {
        "配穴" : "少澤",
        "治療" : "攀睛"
      },
      {
        "配穴" : "命門",
        "治療" : "目不明"
      },
      {
        "配穴" : "翳明、中封",
        "治療" : "急性傳染性肝炎"
      },
      {
        "配穴" : "脾兪、期門、督兪、血海、陽陵泉、三陰交",
        "治療" : "肝硬化"
      },
      {
        "配穴" : "膽兪、腕骨、陽陵泉、足臨泣、行間",
        "治療" : "膽石痛"
      },
      {
        "配穴" : "氣海、三陰交",
        "治療" : "閉經"
      },
      {
        "配穴" : "腎兪、風池、角孫、太陽、攢竹、合谷",
        "治療" : "視神經萎縮，視網膜出血"
      },
      {
        "配穴" : "啞門、臨泣、內庭",
        "治療" : "衂血"
      },
      {
        "配穴" : "腎兪、風池、百會、太陽、神門",
        "治療" : "頭痛、頭暈、失眠、神經衰弱"
      },
      {
        "配穴" : " ",
        "治療" : "生殖器疾病"
      },
      {
        "配穴" : " ",
        "治療" : "肝臟疾病，膽囊疾病"
      },
      {
        "配穴" : " ",
        "治療" : "一切眼疾"
      },
      {
        "配穴" : " ",
        "治療" : "治慢性肝炎、肝硬化"
      },
      {
        "配穴" : " ",
        "治療" : "美容、消除疲勞"
      },
      {
        "配穴" : " ",
        "治療" : "額痛、偏頭痛"
      },
      {
        "配穴" : " ",
        "治療" : "肋間神經痛與胸膜炎"
      },
      {
        "配穴" : " ",
        "治療" : "失眠症的反應點與治療點"
      },
      {
        "配穴" : " ",
        "治療" : "治神經衰弱，失眠"
      },
      {
        "配穴" : " ",
        "治療" : "治療瘰癧特效穴"
      },
      {
        "配穴" : " ",
        "治療" : "灸肝兪可強壯，治失眠"
      }
    ]
  }
  