{
    "郄門": [
      {
        "配穴": "尺澤、肺兪",
        "治療": "咳血"
      },
      {
        "配穴": "神門、心兪",
        "治療": "心悸，心絞痛"
      },
      {
        "配穴": "中脘、膈兪",
        "治療": "嘔吐，嘔血"
      },
      {
        "配穴": "曲池、三陽絡",
        "治療": "咯血"
      },
      {
        "配穴": "內關、膈兪",
        "治療": "心胸痛"
      },
      {
        "配穴": "三陽絡",
        "治療": "針麻胸腔手術"
      },
      {
        "配穴": "灸膏肓",
        "治療": "脇膜炎"
      },
      {
        "配穴": "灸章門",
        "治療": "胸膜炎"
      },
      {
        "配穴": "四瀆、外關",
        "治療": "胸膜炎"
      }
    ]
  }
  